README.md
setup.py
sqlorm4es/__init__.py
sqlorm4es/compiler.py
sqlorm4es/epool.py
sqlorm4es/field.py
sqlorm4es/model.py
sqlorm4es/query.py
sqlorm4es/sql.py
sqlorm4es/utils.py
sqlorm4es.egg-info/PKG-INFO
sqlorm4es.egg-info/SOURCES.txt
sqlorm4es.egg-info/dependency_links.txt
sqlorm4es.egg-info/not-zip-safe
sqlorm4es.egg-info/requires.txt
sqlorm4es.egg-info/top_level.txt
test/test_compiler.py
test/test_model.py
test/test_query.py