Metadata-Version: 2.1
Name: sqlorm4es
Version: 1.1.4
Summary: A simple, expressive elasticsearch orm
Home-page: https://github.com/floatliang/sqlorm4es
Author: floatsliang
Author-email: utavianus@qq.com
License: UNKNOWN
Keywords: sql orm elasticsearch
Platform: any
Classifier: Development Status :: 4 - Beta
Classifier: Intended Audience :: Developers
Classifier: Topic :: Software Development :: Libraries :: Python Modules
Classifier: License :: OSI Approved :: MIT License
Classifier: Operating System :: OS Independent
Classifier: Programming Language :: Python :: 3
Classifier: Programming Language :: Python :: 3.4
Classifier: Programming Language :: Python :: 3.5
Classifier: Programming Language :: Python :: 3.6
Classifier: Programming Language :: Python :: 3.7
